listcord/__init__.py
listcord.py-1.5.0.dist-info/METADATA
listcord.py-1.5.0.dist-info/WHEEL
listcord.py-1.5.0.dist-info/top_level.txt
listcord.py-1.5.0.dist-info/RECORD
