Metadata-Version: 2.1
Name: listcord.py
Version: 1.5.0
Summary: Simple listcord api wrapper for python!
Home-page: https://github.com/listcordteam/listcord.py
License: MIT
Keywords: listcord
Platform: UNKNOWN
Classifier: License :: OSI Approved :: MIT License
Classifier: Programming Language :: Python :: 3
Classifier: Programming Language :: Python :: 3.7
